SOLIDserverRest/Exception.py
SOLIDserverRest/SOLIDserverRest.py
SOLIDserverRest/__init__.py
SOLIDserverRest/mapper.py
SOLIDserverRest/adv/__init__.py
SOLIDserverRest/adv/base.py
SOLIDserverRest/adv/class_params.py
SOLIDserverRest/adv/device.py
SOLIDserverRest/adv/device_tools.py
SOLIDserverRest/adv/devif.py
SOLIDserverRest/adv/dns.py
SOLIDserverRest/adv/dns_record.py
SOLIDserverRest/adv/dns_view.py
SOLIDserverRest/adv/dns_zone.py
SOLIDserverRest/adv/ipaddress.py
SOLIDserverRest/adv/network.py
SOLIDserverRest/adv/nom_folder.py
SOLIDserverRest/adv/nom_interface.py
SOLIDserverRest/adv/nom_network_object.py
SOLIDserverRest/adv/sds.py
SOLIDserverRest/adv/space.py
SOLIDserverRest/adv/validators.py
solidserverrest-2.12.3.dist-info/licenses/LICENSE
solidserverrest-2.12.3.dist-info/METADATA
solidserverrest-2.12.3.dist-info/WHEEL
solidserverrest-2.12.3.dist-info/entry_points.txt
solidserverrest-2.12.3.dist-info/top_level.txt
solidserverrest-2.12.3.dist-info/RECORD
