Metadata-Version: 2.4
Name: SOLIDserverRest
Version: 2.12.3
Summary: The SOLIDserverRest is a library to drive EfficientIP API
Home-page: https://gitlab.com/efficientip/solidserverrest
Author: Gregory CUGAT / Alex Chauvin
Author-email: gregory.cugat@efficientip.com, ach@efficientip.com
License: BSD 2
Classifier: Intended Audience :: Developers
Classifier: Programming Language :: Python :: 3.9
Classifier: Programming Language :: Python :: 3.10
Classifier: Programming Language :: Python :: 3.11
Classifier: Programming Language :: Python :: 3.12
Classifier: Programming Language :: Python :: 3.13
Requires-Python: >=3.9
License-File: LICENSE
Requires-Dist: requests~=2.32
Requires-Dist: urllib3~=2.5
Requires-Dist: idna~=3.11
Requires-Dist: PySocks~=1.7
Requires-Dist: chardet~=5.2
Requires-Dist: pyopenssl~=25.3
Requires-Dist: packaging>=24.0
Requires-Dist: macaddress~=2.0
Dynamic: author
Dynamic: author-email
Dynamic: classifier
Dynamic: description
Dynamic: description-content-type
Dynamic: home-page
Dynamic: license
Dynamic: license-file
Dynamic: requires-dist
Dynamic: requires-python
Dynamic: summary
